parsable.py
parsable-0.3.2.data/data/parsable.pyi
parsable-0.3.2.dist-info/METADATA
parsable-0.3.2.dist-info/WHEEL
parsable-0.3.2.dist-info/top_level.txt
parsable-0.3.2.dist-info/RECORD
