Metadata-Version: 2.4
Name: parsable
Version: 0.3.2
Summary: Lightweight argument parsing using a decorator
Home-page: https://github.com/fritzo/parsable
Author: Fritz Obermeyer
Author-email: fritz.obermeyer@gmail.com
Dynamic: author
Dynamic: author-email
Dynamic: description
Dynamic: home-page
Dynamic: summary
